bpmagic.py
bpmagic-0.13.1.dist-info/DESCRIPTION.rst
bpmagic-0.13.1.dist-info/METADATA
bpmagic-0.13.1.dist-info/RECORD
bpmagic-0.13.1.dist-info/WHEEL
bpmagic-0.13.1.dist-info/metadata.json
bpmagic-0.13.1.dist-info/top_level.txt
