Metadata-Version: 2.0
Name: bpmagic
Version: 0.13.1
Summary: Magic functions to load boilerplate code
Home-page: https://github.com/pm8k/bpmagic
Author: Matthew Russell
Author-email: astromars42@gmail.com
License: MIT
Download-URL: https://github.com/pm8k/bpmagic/archive/0.13.1.tar.gz
Keywords: python,magic,jupyter,ipython,boiler,plate,bp
Platform: UNKNOWN
Classifier: Framework :: IPython
Requires-Dist: ipython
